http_client/__init__.py
http_client/client.py
http_client_async-0.1.4.dist-info/METADATA
http_client_async-0.1.4.dist-info/WHEEL
http_client_async-0.1.4.dist-info/top_level.txt
http_client_async-0.1.4.dist-info/RECORD
