Metadata-Version: 2.1
Name: http-client-async
Version: 0.1.4
Author-email: Mike Artemiev <mixartemev@gmail.com>
Project-URL: Homepage, https://github.com/mixartemev/http-client
Project-URL: Repository, https://github.com/mixartemev/http-client
Requires-Python: >=3.11
Requires-Dist: aiohttp
